fiberfox/__init__.py
fiberfox/main.py
fiberfox/qrator.py
fiberfox/static.py
fiberfox-0.3.7.dist-info/LICENSE
fiberfox-0.3.7.dist-info/METADATA
fiberfox-0.3.7.dist-info/WHEEL
fiberfox-0.3.7.dist-info/entry_points.txt
fiberfox-0.3.7.dist-info/top_level.txt
fiberfox-0.3.7.dist-info/RECORD
