Metadata-Version: 2.1
Name: fiberfox
Version: 0.3.7
Summary: High-performance (D)DoS vulnerability testing toolkit. Various L4/7 attack vectors. Async networking.
Home-page: https://github.com/kachayev/fiberfox
Author: Oleksii Kachaiev
Author-email: kachayev@gmail.com
License: MIT
Keywords: network
Platform: UNKNOWN
Classifier: Development Status :: 5 - Production/Stable
Classifier: Environment :: Console
Classifier: Intended Audience :: Developers
Classifier: Intended Audience :: Information Technology
Classifier: Intended Audience :: System Administrators
Classifier: Intended Audience :: Telecommunications Industry
Classifier: License :: OSI Approved :: MIT License
Classifier: Programming Language :: Python :: 3 :: Only
Classifier: Programming Language :: Python :: 3.8
Classifier: Programming Language :: Python :: 3.9
Classifier: Topic :: Security
Classifier: Topic :: System :: Networking
Classifier: Topic :: System :: Networking :: Monitoring
Requires-Python: >=3.8
License-File: LICENSE
Requires-Dist: asks (==2.4.12)
Requires-Dist: certifi (==2021.10.8)
Requires-Dist: curio (==1.5)
Requires-Dist: dnspython (==2.2.1)
Requires-Dist: impacket (==0.9.23)
Requires-Dist: python-socks (==2.0.3)
Requires-Dist: sparklines (==0.4.2)
Requires-Dist: tabulate (==0.8.9)
Requires-Dist: yarl (~=1.7.2)
